setup.py
distributions_tt/Binomialdistribution.py
distributions_tt/Gaussiandistribution.py
distributions_tt/Generaldistribution.py
distributions_tt/__init__.py
distributions_tt.egg-info/PKG-INFO
distributions_tt.egg-info/SOURCES.txt
distributions_tt.egg-info/dependency_links.txt
distributions_tt.egg-info/not-zip-safe
distributions_tt.egg-info/top_level.txt